sayrevolution/__init__.py
sayrevolution-0.2.0.dist-info/entry_points.txt
sayrevolution-0.2.0.dist-info/WHEEL
sayrevolution-0.2.0.dist-info/METADATA
sayrevolution-0.2.0.dist-info/RECORD
