Metadata-Version: 2.1
Name: sayrevolution
Version: 0.2.0
Summary: It says revolution
Author: Sam Lavigne
Author-email: splavigne@gmail.com
Requires-Python: >=3.9,<4.0
Classifier: Programming Language :: Python :: 3
Classifier: Programming Language :: Python :: 3.10
Classifier: Programming Language :: Python :: 3.9
